README.rst
setup.py
pyutils_sh/__init__.py
pyutils_sh/battery.py
pyutils_sh/exam.py
pyutils_sh/gaze.py
pyutils_sh/image.py
pyutils_sh/stats.py
pyutils_sh/survey.py
pyutils_sh/utils.py
pyutils_sh/version.py
pyutils_sh.egg-info/PKG-INFO
pyutils_sh.egg-info/SOURCES.txt
pyutils_sh.egg-info/dependency_links.txt
pyutils_sh.egg-info/requires.txt
pyutils_sh.egg-info/top_level.txt
pyutils_sh.egg-info/zip-safe