Metadata-Version: 1.2
Name: pyutils-sh
Version: 1.5.1
Summary: Assortment of Python utilities for my personal projects
Home-page: https://github.com/sho-87/pyutils_sh
Author: Simon Ho
Author-email: simonho213@gmail.com
License: MIT
Keywords: python utilities survey exam gaze spss data research statistics
Platform: UNKNOWN
Classifier: Development Status :: 5 - Production/Stable
Classifier: Intended Audience :: Science/Research
Classifier: License :: OSI Approved :: MIT License
Classifier: Operating System :: OS Independent
Classifier: Programming Language :: Python :: 3
Classifier: Topic :: Scientific/Engineering
Requires-Python: >=3
